aiowebdav2/__init__.py
aiowebdav2/client.py
aiowebdav2/exceptions.py
aiowebdav2/models.py
aiowebdav2/parser.py
aiowebdav2/py.typed
aiowebdav2/typing_helper.py
aiowebdav2/urn.py
aiowebdav2-0.5.0.dist-info/LICENSE
aiowebdav2-0.5.0.dist-info/METADATA
aiowebdav2-0.5.0.dist-info/WHEEL
aiowebdav2-0.5.0.dist-info/RECORD
