Metadata-Version: 2.3
Name: aiowebdav2
Version: 0.5.0
Summary: Async Python 3 client for WebDAV, based on aiowebdav and https://github.com/ezhov-evgeny/webdav-client-python-3
License: MIT
Author: Jan-Philipp Benecke
Author-email: jan-philipp@bnck.me
Requires-Python: >=3.11,<4.0
Classifier: Development Status :: 5 - Production/Stable
Classifier: Framework :: AsyncIO
Classifier: Intended Audience :: Developers
Classifier: License :: OSI Approved :: MIT License
Classifier: Natural Language :: English
Classifier: Programming Language :: Python :: 3
Classifier: Programming Language :: Python :: 3.11
Classifier: Programming Language :: Python :: 3.12
Classifier: Programming Language :: Python :: 3.13
Classifier: Topic :: Software Development :: Libraries :: Python Modules
Requires-Dist: aiofiles (>=0.7.0)
Requires-Dist: aiohttp (>=3.8.0)
Requires-Dist: lxml (>=5.3.0)
Requires-Dist: python-dateutil (>=2.9.0.post0)
Requires-Dist: yarl (>=1.18.3)
Project-URL: Bug Tracker, https://github.com/jpbede/aiowebdav2/issues
Project-URL: Changelog, https://github.com/jpbede/aiowebdav2/releases
Project-URL: Repository, https://github.com/jpbede/aiowebdav2
